setup.py
picSearch/SearchServer.py
picSearch/__init__.py
picSearch.egg-info/PKG-INFO
picSearch.egg-info/SOURCES.txt
picSearch.egg-info/dependency_links.txt
picSearch.egg-info/requires.txt
picSearch.egg-info/top_level.txt
picSearch/tools/MilvusTools.py
picSearch/tools/MinioTools.py
picSearch/tools/ResNetEmbeding.py
picSearch/tools/__init__.py